easytz/__init__.py
easytz/convert.py
tests/__init__.py
tests/test_convert.py
easytz-0.1.1.dist-info/LICENSE
easytz-0.1.1.dist-info/METADATA
easytz-0.1.1.dist-info/WHEEL
easytz-0.1.1.dist-info/top_level.txt
easytz-0.1.1.dist-info/RECORD
