Metadata-Version: 2.1
Name: easytz
Version: 0.1.1
Summary: A simple and efficient library for seamless time zone conversions — with built-in batch processing for handling multiple datetime objects effortlessly.
Home-page: https://github.com/vigsun19/easytz
Author: Vignesh Sundaram
Author-email: vigneshanm@gmail.com
Classifier: Programming Language :: Python :: 3
Classifier: License :: OSI Approved :: MIT License
Classifier: Operating System :: OS Independent
Requires-Python: >=3.6
License-File: LICENSE
Requires-Dist: pytz
